{"project_name": "ulo", "phenomenon": "negative", "tuple_size": 4, "replication": 4, "tuples": {"0": [{"id": "1", "text": "\"Hai avuto proprio un colpo di culo a vincere quella lotteria!\""}, {"id": "2", "text": "\"Mi sono fatto un culo cos\u00ec per finire questo progetto in tempo.\""}, {"id": "3", "text": "\"Non aspettarti di risolvere tutto col culo: ci vuole anche impegno.\""}, {"id": "4", "text": "\"Non girare il culo agli amici quando hai successo!\""}], "1": [{"id": "5", "text": "\"Ci metter\u00f2 il culo per raggiungere i miei obiettivi.\""}, {"id": "6", "text": "\"Se continui a fare cos\u00ec, la gente finir\u00e0 per mandarti a fanculo senza pensarci due volte.\""}, {"id": "7", "text": "\"Mi sono seduto tutto il giorno e ora ho il culo a pezzi!\""}, {"id": "8", "text": "\"Ho avuto una giornata pesante e sono pronto a mandare tutti a fanculo.\""}], "2": [{"id": "1", "text": "\"Hai avuto proprio un colpo di culo a vincere quella lotteria!\""}, {"id": "5", "text": "\"Ci metter\u00f2 il culo per raggiungere i miei obiettivi.\""}, {"id": "9", "text": "\"Ho lavorato sodo, ma anche un po' di culo non guasta mai.\""}, {"id": "4", "text": "\"Non girare il culo agli amici quando hai successo!\""}], "3": [{"id": "8", "text": "\"Ho avuto una giornata pesante e sono pronto a mandare tutti a fanculo.\""}, {"id": "3", "text": "\"Non aspettarti di risolvere tutto col culo: ci vuole anche impegno.\""}, {"id": "7", "text": "\"Mi sono seduto tutto il giorno e ora ho il culo a pezzi!\""}, {"id": "2", "text": "\"Mi sono fatto un culo cos\u00ec per finire questo progetto in tempo.\""}], "4": [{"id": "1", "text": "\"Hai avuto proprio un colpo di culo a vincere quella lotteria!\""}, {"id": "8", "text": "\"Ho avuto una giornata pesante e sono pronto a mandare tutti a fanculo.\""}, {"id": "6", "text": "\"Se continui a fare cos\u00ec, la gente finir\u00e0 per mandarti a fanculo senza pensarci due volte.\""}, {"id": "4", "text": "\"Non girare il culo agli amici quando hai successo!\""}], "5": [{"id": "2", "text": "\"Mi sono fatto un culo cos\u00ec per finire questo progetto in tempo.\""}, {"id": "9", "text": "\"Ho lavorato sodo, ma anche un po' di culo non guasta mai.\""}, {"id": "7", "text": "\"Mi sono seduto tutto il giorno e ora ho il culo a pezzi!\""}, {"id": "5", "text": "\"Ci metter\u00f2 il culo per raggiungere i miei obiettivi.\""}], "6": [{"id": "1", "text": "\"Hai avuto proprio un colpo di culo a vincere quella lotteria!\""}, {"id": "2", "text": "\"Mi sono fatto un culo cos\u00ec per finire questo progetto in tempo.\""}, {"id": "3", "text": "\"Non aspettarti di risolvere tutto col culo: ci vuole anche impegno.\""}, {"id": "4", "text": "\"Non girare il culo agli amici quando hai successo!\""}], "7": [{"id": "5", "text": "\"Ci metter\u00f2 il culo per raggiungere i miei obiettivi.\""}, {"id": "6", "text": "\"Se continui a fare cos\u00ec, la gente finir\u00e0 per mandarti a fanculo senza pensarci due volte.\""}, {"id": "7", "text": "\"Mi sono seduto tutto il giorno e ora ho il culo a pezzi!\""}, {"id": "8", "text": "\"Ho avuto una giornata pesante e sono pronto a mandare tutti a fanculo.\""}]}}