{"project_name": "finale?", "phenomenon": "negative", "tuple_size": 6, "replication": 5, "tuples": {"0": [{"id": "1", "text": "\"Hai avuto proprio un colpo di culo a vincere quella lotteria!\""}, {"id": "2", "text": "\"Mi sono fatto un culo cos\u00ec per finire questo progetto in tempo.\""}, {"id": "3", "text": "\"Non aspettarti di risolvere tutto col culo: ci vuole anche impegno.\""}, {"id": "4", "text": "\"Non girare il culo agli amici quando hai successo!\""}, {"id": "5", "text": "\"Ci metter\u00f2 il culo per raggiungere i miei obiettivi.\""}, {"id": "6", "text": "\"Se continui a fare cos\u00ec, la gente finir\u00e0 per mandarti a fanculo senza pensarci due volte.\""}], "1": [{"id": "1", "text": "\"Hai avuto proprio un colpo di culo a vincere quella lotteria!\""}, {"id": "7", "text": "\"Mi sono seduto tutto il giorno e ora ho il culo a pezzi!\""}, {"id": "6", "text": "\"Se continui a fare cos\u00ec, la gente finir\u00e0 per mandarti a fanculo senza pensarci due volte.\""}, {"id": "5", "text": "\"Ci metter\u00f2 il culo per raggiungere i miei obiettivi.\""}, {"id": "4", "text": "\"Non girare il culo agli amici quando hai successo!\""}, {"id": "3", "text": "\"Non aspettarti di risolvere tutto col culo: ci vuole anche impegno.\""}], "2": [{"id": "1", "text": "\"Hai avuto proprio un colpo di culo a vincere quella lotteria!\""}, {"id": "2", "text": "\"Mi sono fatto un culo cos\u00ec per finire questo progetto in tempo.\""}, {"id": "3", "text": "\"Non aspettarti di risolvere tutto col culo: ci vuole anche impegno.\""}, {"id": "4", "text": "\"Non girare il culo agli amici quando hai successo!\""}, {"id": "5", "text": "\"Ci metter\u00f2 il culo per raggiungere i miei obiettivi.\""}, {"id": "6", "text": "\"Se continui a fare cos\u00ec, la gente finir\u00e0 per mandarti a fanculo senza pensarci due volte.\""}], "3": [{"id": "1", "text": "\"Hai avuto proprio un colpo di culo a vincere quella lotteria!\""}, {"id": "7", "text": "\"Mi sono seduto tutto il giorno e ora ho il culo a pezzi!\""}, {"id": "6", "text": "\"Se continui a fare cos\u00ec, la gente finir\u00e0 per mandarti a fanculo senza pensarci due volte.\""}, {"id": "5", "text": "\"Ci metter\u00f2 il culo per raggiungere i miei obiettivi.\""}, {"id": "4", "text": "\"Non girare il culo agli amici quando hai successo!\""}, {"id": "3", "text": "\"Non aspettarti di risolvere tutto col culo: ci vuole anche impegno.\""}], "4": [{"id": "1", "text": "\"Hai avuto proprio un colpo di culo a vincere quella lotteria!\""}, {"id": "2", "text": "\"Mi sono fatto un culo cos\u00ec per finire questo progetto in tempo.\""}, {"id": "3", "text": "\"Non aspettarti di risolvere tutto col culo: ci vuole anche impegno.\""}, {"id": "4", "text": "\"Non girare il culo agli amici quando hai successo!\""}, {"id": "5", "text": "\"Ci metter\u00f2 il culo per raggiungere i miei obiettivi.\""}, {"id": "6", "text": "\"Se continui a fare cos\u00ec, la gente finir\u00e0 per mandarti a fanculo senza pensarci due volte.\""}]}}